charset/__init__.py
charset/charset.py
charset/encoding.py
charset/unicode.py
unicode_charset-0.0.0.dist-info/LICENSE
unicode_charset-0.0.0.dist-info/METADATA
unicode_charset-0.0.0.dist-info/WHEEL
unicode_charset-0.0.0.dist-info/RECORD
