Metadata-Version: 2.1
Name: unicode-charset
Version: 0.0.0
Summary: efficient python generator to yield all characters for a given encoding.
License: MIT
Keywords: charset,unicode
Author: Christoph Dörrer
Author-email: d-chris@web.de
Requires-Python: >=3.9,<4.0
Classifier: License :: OSI Approved :: MIT License
Classifier: Operating System :: OS Independent
Classifier: Programming Language :: Python :: 3
Classifier: Programming Language :: Python :: 3.9
Classifier: Programming Language :: Python :: 3.10
Classifier: Programming Language :: Python :: 3.11
Classifier: Programming Language :: Python :: 3.12
Classifier: Programming Language :: Python :: 3.13
Project-URL: repository, https://github.com/d-chris/unicode-charset
